LICENSE
MANIFEST.in
README.rst
setup.cfg
setup.py
versioneer.py
tpDcc/__init__.py
tpDcc/libs/__init__.py
tpDcc/libs/svg/__init__.py
tpDcc/libs/svg/__logging__.ini
tpDcc/libs/svg/__version__.py
tpDcc/libs/svg/_version.py
tpDcc/libs/svg/core/__init__.py
tpDcc/libs/svg/core/consts.py
tpDcc/libs/svg/core/svglib.py
tpDcc_libs_svg.egg-info/PKG-INFO
tpDcc_libs_svg.egg-info/SOURCES.txt
tpDcc_libs_svg.egg-info/dependency_links.txt
tpDcc_libs_svg.egg-info/not-zip-safe
tpDcc_libs_svg.egg-info/requires.txt
tpDcc_libs_svg.egg-info/top_level.txt