Metadata-Version: 2.1
Name: tpDcc-libs-svg
Version: 0.0.1
Summary: Library to handle SVG files in Python.
Home-page: https://github.com/tpDcc/tpDcc-libs-svg
Author: Tomas Poveda
Author-email: tpovedatd@gmail.com
License: MIT
Platform: UNKNOWN
Provides-Extra: dev
Provides-Extra: test
